ikctl/__init__.py
ikctl/commands.py
ikctl/config.py
ikctl/connect.py
ikctl/context.py
ikctl/create_config_files.py
ikctl/execute.py
ikctl/logs.py
ikctl/main.py
ikctl/pipeline.py
ikctl/sftp.py
ikctl/view.py
ikctl-1.2.2.dist-info/LICENSE
ikctl-1.2.2.dist-info/METADATA
ikctl-1.2.2.dist-info/WHEEL
ikctl-1.2.2.dist-info/entry_points.txt
ikctl-1.2.2.dist-info/top_level.txt
ikctl-1.2.2.dist-info/RECORD
