Metadata-Version: 2.1
Name: ikctl
Version: 1.2.2
Summary: App to installer packages on remote servers
Author: David Moya López
Author-email: 3nueves@gmail.com
License: Apache v2.0
License-File: LICENSE
